gemma_template/__init__.py
gemma_template/__version__.py
gemma_template/constants.py
gemma_template/exceptions.py
gemma_template/models.py
gemma_template/utils.py
tests/__init__.py
tests/conftest.py
tests/test_load_dataset.py
tests/test_template.py
gemma_template-1.0.1.dist-info/LICENSE
gemma_template-1.0.1.dist-info/METADATA
gemma_template-1.0.1.dist-info/WHEEL
gemma_template-1.0.1.dist-info/top_level.txt
gemma_template-1.0.1.dist-info/RECORD
