Metadata-Version: 2.2
Name: gemma-template
Version: 1.0.1
Summary: Gemma Template is a lightweight Python library for generating templates to fine-tune models like Gemma, LLaMa, and others. It supports multilingual frameworks, offers advanced customization, and ensures precise, dynamic template creation.
Home-page: https://github.com/thewebscraping/gemma-template
Author: Tu Pham
Author-email: thetwofarm@gmail.com
License: Apache2
Project-URL: Source, https://github.com/thewebscraping/gemma-template
Project-URL: Homepage, https://github.com/thewebscraping/gemma-template
Classifier: Development Status :: 5 - Production/Stable
Classifier: Intended Audience :: Developers
Classifier: Environment :: Web Environment
Classifier: License :: OSI Approved :: Apache Software License
Classifier: Natural Language :: English
Classifier: Operating System :: OS Independent
Classifier: Programming Language :: Python
Classifier: Programming Language :: Python :: 3
Classifier: Programming Language :: Python :: 3.9
Classifier: Programming Language :: Python :: 3.10
Classifier: Programming Language :: Python :: 3.11
Classifier: Programming Language :: Python :: 3.12
Classifier: Programming Language :: Python :: 3.13
Classifier: Programming Language :: Python :: 3 :: Only
Classifier: Programming Language :: Python :: Implementation :: CPython
Classifier: Programming Language :: Python :: Implementation :: PyPy
Classifier: Topic :: Software Development :: Libraries
Classifier: Topic :: Utilities
License-File: LICENSE
Requires-Dist: Jinja2
Requires-Dist: datasets
Requires-Dist: langdetect
Requires-Dist: nest-asyncio
Requires-Dist: pydantic
Requires-Dist: tqdm
Dynamic: author
Dynamic: author-email
Dynamic: description-content-type
Dynamic: home-page
Dynamic: requires-dist
Dynamic: summary
